rsk7/__init__.py
rsk7/rsk7.py
rsk7-0.0.10.dist-info/LICENSE
rsk7-0.0.10.dist-info/METADATA
rsk7-0.0.10.dist-info/WHEEL
rsk7-0.0.10.dist-info/top_level.txt
rsk7-0.0.10.dist-info/RECORD
